CHANGES.txt
CONTRIBUTORS.txt
README.txt
bootstrap.py
buildout.cfg
setup.py
topp/__init__.py
topp.recipes.securemaildrop.egg-info/PKG-INFO
topp.recipes.securemaildrop.egg-info/SOURCES.txt
topp.recipes.securemaildrop.egg-info/dependency_links.txt
topp.recipes.securemaildrop.egg-info/entry_points.txt
topp.recipes.securemaildrop.egg-info/namespace_packages.txt
topp.recipes.securemaildrop.egg-info/not-zip-safe
topp.recipes.securemaildrop.egg-info/requires.txt
topp.recipes.securemaildrop.egg-info/top_level.txt
topp/recipes/__init__.py
topp/recipes/securemaildrop/README.txt
topp/recipes/securemaildrop/__init__.py
topp/recipes/securemaildrop/ctl.py
topp/recipes/securemaildrop/tests/__init__.py
topp/recipes/securemaildrop/tests/test_docs.py