Metadata-Version: 1.0
Name: topp.recipes.securemaildrop
Version: 0.1.4
Summary: Install MaildropHost and SecureMaildrop Zope products and maildrop daemon
Home-page: UNKNOWN
Author: TOPP
Author-email: info@openplans.org
License: ZPL
Platform: UNKNOWN
Classifier: Framework :: Buildout
Classifier: Intended Audience :: Developers
Classifier: Topic :: Software Development :: Build Tools
Classifier: Topic :: Software Development :: Libraries :: Python Modules
Classifier: License :: OSI Approved :: Zope Public License
